{"12": {"0": ["", 100, ["giSteedQgrT3iaaBhBUxA7", "DB7NzKVzzpcmiyFqpz28GJ", "VRHFHYNHpXMwfHyLvS6jTS", "2Fbcu4RwHuSpMjHG9hiTEr", "LccBsXvdFnxDUcsP5yiqWQ"]]}, "8": {"0": ["gmain", 5, ["giSteedQgrT3iaaBhBUxA7", "DB7NzKVzzpcmiyFqpz28GJ", "VRHFHYNHpXMwfHyLvS6jTS"]], "1": ["auditd", 1, ["giSteedQgrT3iaaBhBUxA7"]], "2": ["sudo", 36, ["giSteedQgrT3iaaBhBUxA7", "DB7NzKVzzpcmiyFqpz28GJ"]], "3": ["file", 18, ["giSteedQgrT3iaaBhBUxA7", "DB7NzKVzzpcmiyFqpz28GJ", "2Fbcu4RwHuSpMjHG9hiTEr", "LccBsXvdFnxDUcsP5yiqWQ"]], "4": ["login.defs", 7, ["giSteedQgrT3iaaBhBUxA7", "DB7NzKVzzpcmiyFqpz28GJ"]], "5": ["netlink", 3, ["giSteedQgrT3iaaBhBUxA7", "DB7NzKVzzpcmiyFqpz28GJ"]], "6": ["audit.sh", 55, ["DB7NzKVzzpcmiyFqpz28GJ", "VRHFHYNHpXMwfHyLvS6jTS", "2Fbcu4RwHuSpMjHG9hiTEr", "LccBsXvdFnxDUcsP5yiqWQ"]], "7": ["pipe", 2, ["VRHFHYNHpXMwfHyLvS6jTS"]], "8": [".", 1, ["2Fbcu4RwHuSpMjHG9hiTEr"]], "9": ["pidof", 12, ["2Fbcu4RwHuSpMjHG9hiTEr", "LccBsXvdFnxDUcsP5yiqWQ"]], "10": ["pidof.sh", 1, ["LccBsXvdFnxDUcsP5yiqWQ"]]}, "9": {"0": ["1", 8, ["giSteedQgrT3iaaBhBUxA7", "DB7NzKVzzpcmiyFqpz28GJ", "VRHFHYNHpXMwfHyLvS6jTS", "2Fbcu4RwHuSpMjHG9hiTEr"]], "1": ["0", 78, ["giSteedQgrT3iaaBhBUxA7", "DB7NzKVzzpcmiyFqpz28GJ", "VRHFHYNHpXMwfHyLvS6jTS", "2Fbcu4RwHuSpMjHG9hiTEr", "LccBsXvdFnxDUcsP5yiqWQ"]], "2": ["2", 1, ["giSteedQgrT3iaaBhBUxA7"]], "3": ["1236", 5, ["giSteedQgrT3iaaBhBUxA7", "DB7NzKVzzpcmiyFqpz28GJ", "VRHFHYNHpXMwfHyLvS6jTS"]], "4": ["49011", 38, ["giSteedQgrT3iaaBhBUxA7", "DB7NzKVzzpcmiyFqpz28GJ"]], "5": ["49012", 2, ["giSteedQgrT3iaaBhBUxA7"]], "6": ["49005", 94, ["giSteedQgrT3iaaBhBUxA7", "DB7NzKVzzpcmiyFqpz28GJ", "VRHFHYNHpXMwfHyLvS6jTS", "2Fbcu4RwHuSpMjHG9hiTEr", "LccBsXvdFnxDUcsP5yiqWQ"]], "7": ["1003", 94, ["giSteedQgrT3iaaBhBUxA7", "DB7NzKVzzpcmiyFqpz28GJ", "VRHFHYNHpXMwfHyLvS6jTS", "2Fbcu4RwHuSpMjHG9hiTEr", "LccBsXvdFnxDUcsP5yiqWQ"]], "8": ["4", 13, ["giSteedQgrT3iaaBhBUxA7", "DB7NzKVzzpcmiyFqpz28GJ", "VRHFHYNHpXMwfHyLvS6jTS"]], "9": ["131246", 7, ["giSteedQgrT3iaaBhBUxA7", "DB7NzKVzzpcmiyFqpz28GJ"]], "10": ["1752604672", 1, ["giSteedQgrT3iaaBhBUxA7"]], "11": ["4096", 2, ["giSteedQgrT3iaaBhBUxA7"]], "12": ["2359", 1, ["giSteedQgrT3iaaBhBUxA7"]], "13": ["5", 1, ["giSteedQgrT3iaaBhBUxA7"]], "14": ["78", 1, ["giSteedQgrT3iaaBhBUxA7"]], "15": ["120", 1, ["giSteedQgrT3iaaBhBUxA7"]], "16": ["36", 2, ["giSteedQgrT3iaaBhBUxA7", "DB7NzKVzzpcmiyFqpz28GJ"]], "17": ["29447", 14, ["DB7NzKVzzpcmiyFqpz28GJ", "VRHFHYNHpXMwfHyLvS6jTS"]], "18": ["3", 1, ["VRHFHYNHpXMwfHyLvS6jTS"]], "19": ["685", 1, ["VRHFHYNHpXMwfHyLvS6jTS"]], "20": ["49017", 44, ["VRHFHYNHpXMwfHyLvS6jTS", "2Fbcu4RwHuSpMjHG9hiTEr", "LccBsXvdFnxDUcsP5yiqWQ"]], "21": ["700170", 1, ["2Fbcu4RwHuSpMjHG9hiTEr"]], "22": ["129", 11, ["2Fbcu4RwHuSpMjHG9hiTEr", "LccBsXvdFnxDUcsP5yiqWQ"]], "23": ["32616", 1, ["LccBsXvdFnxDUcsP5yiqWQ"]], "24": ["13791232", 1, ["LccBsXvdFnxDUcsP5yiqWQ"]], "25": ["-1655648256", 1, ["LccBsXvdFnxDUcsP5yiqWQ"]]}, "13": {"0": ["/usr/lib/accountsservice/accounts-daemon", 5, ["giSteedQgrT3iaaBhBUxA7", "DB7NzKVzzpcmiyFqpz28GJ", "VRHFHYNHpXMwfHyLvS6jTS"]], "1": ["netlink_pid:0", 3, ["giSteedQgrT3iaaBhBUxA7", "DB7NzKVzzpcmiyFqpz28GJ"]], "2": ["netlink_family:16", 3, ["giSteedQgrT3iaaBhBUxA7", "DB7NzKVzzpcmiyFqpz28GJ"]], "3": ["-1700926496_32616.-1700926496", 1, ["LccBsXvdFnxDUcsP5yiqWQ"]]}, "6": {"0": ["0.000_0_0", 100, ["giSteedQgrT3iaaBhBUxA7", "DB7NzKVzzpcmiyFqpz28GJ", "VRHFHYNHpXMwfHyLvS6jTS", "2Fbcu4RwHuSpMjHG9hiTEr", "LccBsXvdFnxDUcsP5yiqWQ"]]}, "5": {"0": ["1236_1471074506.946", 5, ["giSteedQgrT3iaaBhBUxA7", "DB7NzKVzzpcmiyFqpz28GJ", "VRHFHYNHpXMwfHyLvS6jTS"]], "1": ["49012_1471074506.934", 1, ["giSteedQgrT3iaaBhBUxA7"]], "2": ["49011_1471074506.930", 36, ["giSteedQgrT3iaaBhBUxA7", "DB7NzKVzzpcmiyFqpz28GJ"]], "3": ["49005_1471074506.922", 14, ["DB7NzKVzzpcmiyFqpz28GJ", "VRHFHYNHpXMwfHyLvS6jTS"]], "4": ["49017_1471074506.950", 41, ["VRHFHYNHpXMwfHyLvS6jTS", "2Fbcu4RwHuSpMjHG9hiTEr", "LccBsXvdFnxDUcsP5yiqWQ"]], "5": ["49017_1471074506.954", 2, ["LccBsXvdFnxDUcsP5yiqWQ"]]}, "3": {"0": ["a[0]=0x7fc7780008c0 a[1]=0x2 a[2]=0x3c2", 3, ["giSteedQgrT3iaaBhBUxA7", "DB7NzKVzzpcmiyFqpz28GJ"]], "1": ["a[0]=0x0", 3, ["giSteedQgrT3iaaBhBUxA7", "DB7NzKVzzpcmiyFqpz28GJ", "LccBsXvdFnxDUcsP5yiqWQ"]], "2": ["a[0]=0x55dbbfbd0d60 a[1]=0x1 a[2]=0xffffffff", 1, ["giSteedQgrT3iaaBhBUxA7"]], "3": ["a[0]=0xbf74 a[1]=0x7fffa0e147ec a[2]=0x3 a[3]=0x0", 1, ["giSteedQgrT3iaaBhBUxA7"]], "4": ["a[0]=0x0 a[1]=0x0 a[2]=0x7fc4669ffd08 a[3]=0x8", 1, ["giSteedQgrT3iaaBhBUxA7"]], "5": ["a[0]=0x7fc465f6843c a[1]=0x0 a[2]=0x1b6", 1, ["giSteedQgrT3iaaBhBUxA7"]], "6": ["a[0]=0x4 a[1]=0x7fffa0e14830", 1, ["giSteedQgrT3iaaBhBUxA7"]], "7": ["a[0]=0x0 a[1]=0x1000 a[2]=0x3 a[3]=0x22", 1, ["giSteedQgrT3iaaBhBUxA7"]], "8": ["a[0]=0x4 a[1]=0x7fc46876a000 a[2]=0x1000", 3, ["giSteedQgrT3iaaBhBUxA7"]], "9": ["a[0]=0x4", 3, ["giSteedQgrT3iaaBhBUxA7", "DB7NzKVzzpcmiyFqpz28GJ", "VRHFHYNHpXMwfHyLvS6jTS"]], "10": ["a[0]=0x7fc46876a000 a[1]=0x1000", 1, ["giSteedQgrT3iaaBhBUxA7"]], "11": ["a[0]=0x5 a[1]=0x55dbbfbdc420 a[2]=0x4e a[3]=0x4000", 1, ["giSteedQgrT3iaaBhBUxA7"]], "12": ["a[0]=0x10 a[1]=0x3 a[2]=0x9", 1, ["giSteedQgrT3iaaBhBUxA7"]], "13": ["a[0]=0x4 a[1]=0x2 a[2]=0x1", 1, ["giSteedQgrT3iaaBhBUxA7"]], "14": ["a[0]=0x4 a[1]=0x7fffa0e0df30 a[2]=0x78 a[3]=0x0", 1, ["giSteedQgrT3iaaBhBUxA7"]], "15": ["a[0]=0x7fffa0e0df10 a[1]=0x1 a[2]=0x1f4", 1, ["giSteedQgrT3iaaBhBUxA7"]], "16": ["a[0]=0x4 a[1]=0x7fffa0e10260 a[2]=0x231c a[3]=0x42", 1, ["giSteedQgrT3iaaBhBUxA7"]], "17": ["a[0]=0x4 a[1]=0x7fffa0e10260 a[2]=0x231c a[3]=0x40", 1, ["DB7NzKVzzpcmiyFqpz28GJ"]], "18": ["a[0]=0x7fc466178000 a[1]=0x2030e8", 1, ["DB7NzKVzzpcmiyFqpz28GJ"]], "19": ["a[0]=0x7fc465f5d000 a[1]=0x21a400", 1, ["DB7NzKVzzpcmiyFqpz28GJ"]], "20": ["a[0]=0x7fc465d24000 a[1]=0x238220", 1, ["DB7NzKVzzpcmiyFqpz28GJ"]], "21": ["a[0]=0x7fc465b22000 a[1]=0x201038", 1, ["DB7NzKVzzpcmiyFqpz28GJ"]], "22": ["a[0]=0x7fc465920000 a[1]=0x201048", 1, ["DB7NzKVzzpcmiyFqpz28GJ"]], "23": ["a[0]=0x7fc46571d000 a[1]=0x2020f0", 1, ["DB7NzKVzzpcmiyFqpz28GJ"]], "24": ["a[0]=0x7fc465315000 a[1]=0x2020f0", 1, ["DB7NzKVzzpcmiyFqpz28GJ"]], "25": ["a[0]=0x7fc46510a000 a[1]=0x20a300", 1, ["DB7NzKVzzpcmiyFqpz28GJ"]], "26": ["a[0]=0x7fc464eff000 a[1]=0x20a850", 1, ["DB7NzKVzzpcmiyFqpz28GJ"]], "27": ["a[0]=0x7fc465518000 a[1]=0x204270", 1, ["DB7NzKVzzpcmiyFqpz28GJ"]], "28": ["a[0]=0x7fc464ce4000 a[1]=0x21a028", 1, ["DB7NzKVzzpcmiyFqpz28GJ"]], "29": ["a[0]=0x7fc4648c2000 a[1]=0x209018", 1, ["DB7NzKVzzpcmiyFqpz28GJ"]], "30": ["a[0]=0x7fc464acc000 a[1]=0x2171a0", 1, ["DB7NzKVzzpcmiyFqpz28GJ"]], "31": ["a[0]=0x7fc46467d000 a[1]=0x2446c0", 1, ["DB7NzKVzzpcmiyFqpz28GJ"]], "32": ["a[0]=0x7fc464479000 a[1]=0x203140", 1, ["DB7NzKVzzpcmiyFqpz28GJ"]], "33": ["a[0]=0x7fc7780008c0 a[1]=0x1 a[2]=0xa", 2, ["DB7NzKVzzpcmiyFqpz28GJ", "VRHFHYNHpXMwfHyLvS6jTS"]], "34": ["a[0]=0x7fffffffffffffff a[1]=0x7fffe55fc928 a[2]=0x0 a[3]=0x0", 1, ["DB7NzKVzzpcmiyFqpz28GJ"]], "35": ["a[0]=0x2 a[1]=0x7fffe55fc6c0 a[2]=0x7fffe55fc760 a[3]=0x8", 1, ["VRHFHYNHpXMwfHyLvS6jTS"]], "36": ["a[0]=0x2 a[1]=0x7fffe55fc9f0 a[2]=0x0 a[3]=0x8", 1, ["VRHFHYNHpXMwfHyLvS6jTS"]], "37": ["a[0]=0x0 a[1]=0x0 a[2]=0x7fffe55fc8b0 a[3]=0x8", 1, ["VRHFHYNHpXMwfHyLvS6jTS"]], "38": ["a[0]=0x7fffe55fc940", 1, ["VRHFHYNHpXMwfHyLvS6jTS"]], "39": ["a[0]=0x0 a[1]=0x7fffe55fc7f0 a[2]=0x7fffe55fc870 a[3]=0x8", 1, ["VRHFHYNHpXMwfHyLvS6jTS"]], "40": ["a[0]=0x2 a[1]=0x7fffe55fc870 a[2]=0x0 a[3]=0x8", 1, ["VRHFHYNHpXMwfHyLvS6jTS"]], "41": ["a[0]=0x0 a[1]=0x7fffe55fc7d0 a[2]=0x7fffe55fc850 a[3]=0x8", 1, ["VRHFHYNHpXMwfHyLvS6jTS"]], "42": ["a[0]=0xff a[1]=0x7fffffffffffffff a[2]=0x1", 1, ["VRHFHYNHpXMwfHyLvS6jTS"]], "43": ["a[0]=0x1200011 a[1]=0x0 a[2]=0x0 a[3]=0x7fe006025a10", 1, ["VRHFHYNHpXMwfHyLvS6jTS"]], "44": ["a[0]=0x2 a[1]=0x7fffe55fc850 a[2]=0x0 a[3]=0x8", 1, ["VRHFHYNHpXMwfHyLvS6jTS"]], "45": ["a[0]=0x11 a[1]=0x7fffe55fc660 a[2]=0x7fffe55fc700 a[3]=0x8", 2, ["VRHFHYNHpXMwfHyLvS6jTS", "2Fbcu4RwHuSpMjHG9hiTEr"]], "46": ["a[0]=0x2 a[1]=0x6fe2e0 a[2]=0x0 a[3]=0x8", 1, ["VRHFHYNHpXMwfHyLvS6jTS"]], "47": ["a[0]=0x14 a[1]=0x7fffe55fc510 a[2]=0x7fffe55fc5b0 a[3]=0x8", 1, ["VRHFHYNHpXMwfHyLvS6jTS"]], "48": ["a[0]=0x15 a[1]=0x7fffe55fc510 a[2]=0x7fffe55fc5b0 a[3]=0x8", 1, ["VRHFHYNHpXMwfHyLvS6jTS"]], "49": ["a[0]=0x16 a[1]=0x7fffe55fc520 a[2]=0x7fffe55fc5c0 a[3]=0x8", 1, ["VRHFHYNHpXMwfHyLvS6jTS"]], "50": ["a[0]=0x2 a[1]=0x7fffe55fc630 a[2]=0x7fffe55fc6d0 a[3]=0x8", 1, ["VRHFHYNHpXMwfHyLvS6jTS"]], "51": ["a[0]=0x3 a[1]=0x7fffe55fc630 a[2]=0x7fffe55fc6d0 a[3]=0x8", 1, ["VRHFHYNHpXMwfHyLvS6jTS"]], "52": ["a[0]=0x11 a[1]=0x7fffe55fc630 a[2]=0x7fffe55fc6d0 a[3]=0x8", 1, ["VRHFHYNHpXMwfHyLvS6jTS"]], "53": ["a[0]=0x2 a[1]=0x7fffe55fc660 a[2]=0x7fffe55fc700 a[3]=0x8", 1, ["2Fbcu4RwHuSpMjHG9hiTEr"]], "54": ["a[0]=0x4 a[1]=0x1", 1, ["2Fbcu4RwHuSpMjHG9hiTEr"]], "55": ["a[0]=0x0 a[1]=0x0 a[2]=0x7fffe55fc850 a[3]=0x8", 1, ["2Fbcu4RwHuSpMjHG9hiTEr"]], "56": ["a[0]=0x4b8b4f a[1]=0x7fffe55fc5b0", 1, ["2Fbcu4RwHuSpMjHG9hiTEr"]], "57": ["a[0]=0xb01c08 a[1]=0x7fffe55fc4c0", 1, ["2Fbcu4RwHuSpMjHG9hiTEr"]], "58": ["a[0]=0xb01c08 a[1]=0x7fffe55fc3f0", 2, ["2Fbcu4RwHuSpMjHG9hiTEr"]], "59": ["a[0]=0xb01c08 a[1]=0x1", 2, ["2Fbcu4RwHuSpMjHG9hiTEr", "LccBsXvdFnxDUcsP5yiqWQ"]], "60": ["a[0]=0xb01c08 a[1]=0x4", 2, ["2Fbcu4RwHuSpMjHG9hiTEr", "LccBsXvdFnxDUcsP5yiqWQ"]], "61": ["a[0]=0xb01c08 a[1]=0x7fffe55fc4f0", 1, ["2Fbcu4RwHuSpMjHG9hiTEr"]], "62": ["a[0]=0xb01c08 a[1]=0x7fffe55fc420", 2, ["2Fbcu4RwHuSpMjHG9hiTEr", "LccBsXvdFnxDUcsP5yiqWQ"]], "63": ["a[0]=0x2 a[1]=0x7fffe55fc3c0 a[2]=0x7fffe55fc460 a[3]=0x8", 1, ["LccBsXvdFnxDUcsP5yiqWQ"]], "64": ["a[0]=0x3 a[1]=0x7fffe55fc3c0 a[2]=0x7fffe55fc460 a[3]=0x8", 1, ["LccBsXvdFnxDUcsP5yiqWQ"]], "65": ["a[0]=0x11 a[1]=0x7fffe55fc3c0 a[2]=0x7fffe55fc460 a[3]=0x8", 1, ["LccBsXvdFnxDUcsP5yiqWQ"]], "66": ["a[0]=pidofa[1]=auditd", 1, ["LccBsXvdFnxDUcsP5yiqWQ"]], "67": ["a[0]=0xb01c08 a[1]=0xafc988 a[2]=0xafcc08", 1, ["LccBsXvdFnxDUcsP5yiqWQ"]], "68": ["a[0]=0x0 a[1]=0x2000 a[2]=0x3 a[3]=0x22", 1, ["LccBsXvdFnxDUcsP5yiqWQ"]]}, "0": {"0": ["poll(7)", 7, ["giSteedQgrT3iaaBhBUxA7", "DB7NzKVzzpcmiyFqpz28GJ", "VRHFHYNHpXMwfHyLvS6jTS"]], "1": ["exit_group(231)", 2, ["giSteedQgrT3iaaBhBUxA7", "DB7NzKVzzpcmiyFqpz28GJ"]], "2": ["wait4(61)", 2, ["giSteedQgrT3iaaBhBUxA7", "DB7NzKVzzpcmiyFqpz28GJ"]], "3": ["rt_sigprocmask(14)", 9, ["giSteedQgrT3iaaBhBUxA7", "VRHFHYNHpXMwfHyLvS6jTS", "2Fbcu4RwHuSpMjHG9hiTEr"]], "4": ["getuid(102)", 5, ["giSteedQgrT3iaaBhBUxA7", "2Fbcu4RwHuSpMjHG9hiTEr", "LccBsXvdFnxDUcsP5yiqWQ"]], "5": ["open(2)", 1, ["giSteedQgrT3iaaBhBUxA7"]], "6": ["fstat(5)", 1, ["giSteedQgrT3iaaBhBUxA7"]], "7": ["mmap(9)", 2, ["giSteedQgrT3iaaBhBUxA7", "LccBsXvdFnxDUcsP5yiqWQ"]], "8": ["read(0)", 3, ["giSteedQgrT3iaaBhBUxA7"]], "9": ["close(3)", 3, ["giSteedQgrT3iaaBhBUxA7", "DB7NzKVzzpcmiyFqpz28GJ", "VRHFHYNHpXMwfHyLvS6jTS"]], "10": ["munmap(11)", 16, ["giSteedQgrT3iaaBhBUxA7", "DB7NzKVzzpcmiyFqpz28GJ"]], "11": ["sendto(44)", 2, ["giSteedQgrT3iaaBhBUxA7"]], "12": ["socket(41)", 1, ["giSteedQgrT3iaaBhBUxA7"]], "13": ["fcntl(72)", 1, ["giSteedQgrT3iaaBhBUxA7"]], "14": ["recvfrom(45)", 2, ["giSteedQgrT3iaaBhBUxA7", "DB7NzKVzzpcmiyFqpz28GJ"]], "15": ["rt_sigaction(13)", 13, ["VRHFHYNHpXMwfHyLvS6jTS", "2Fbcu4RwHuSpMjHG9hiTEr", "LccBsXvdFnxDUcsP5yiqWQ"]], "16": ["rt_sigreturn(15)", 1, ["VRHFHYNHpXMwfHyLvS6jTS"]], "17": ["pipe(22)", 1, ["VRHFHYNHpXMwfHyLvS6jTS"]], "18": ["lseek(8)", 1, ["VRHFHYNHpXMwfHyLvS6jTS"]], "19": ["clone(56)", 1, ["VRHFHYNHpXMwfHyLvS6jTS"]], "20": ["dup2(33)", 1, ["2Fbcu4RwHuSpMjHG9hiTEr"]], "21": ["stat(4)", 7, ["2Fbcu4RwHuSpMjHG9hiTEr", "LccBsXvdFnxDUcsP5yiqWQ"]], "22": ["geteuid(107)", 4, ["2Fbcu4RwHuSpMjHG9hiTEr", "LccBsXvdFnxDUcsP5yiqWQ"]], "23": ["getegid(108)", 4, ["2Fbcu4RwHuSpMjHG9hiTEr", "LccBsXvdFnxDUcsP5yiqWQ"]], "24": ["getgid(104)", 4, ["2Fbcu4RwHuSpMjHG9hiTEr", "LccBsXvdFnxDUcsP5yiqWQ"]], "25": ["access(21)", 4, ["2Fbcu4RwHuSpMjHG9hiTEr", "LccBsXvdFnxDUcsP5yiqWQ"]], "26": ["execve(59)", 1, ["LccBsXvdFnxDUcsP5yiqWQ"]], "27": ["brk(12)", 1, ["LccBsXvdFnxDUcsP5yiqWQ"]]}, "7": {"0": ["/sbin/auditd", 1, ["giSteedQgrT3iaaBhBUxA7"]], "1": ["/usr/bin/sudo", 36, ["giSteedQgrT3iaaBhBUxA7", "DB7NzKVzzpcmiyFqpz28GJ"]], "2": ["/etc/login.defs", 7, ["giSteedQgrT3iaaBhBUxA7", "DB7NzKVzzpcmiyFqpz28GJ"]], "3": ["/bin/bash", 55, ["DB7NzKVzzpcmiyFqpz28GJ", "VRHFHYNHpXMwfHyLvS6jTS", "2Fbcu4RwHuSpMjHG9hiTEr", "LccBsXvdFnxDUcsP5yiqWQ"]], "4": ["/bin/pidof", 11, ["2Fbcu4RwHuSpMjHG9hiTEr", "LccBsXvdFnxDUcsP5yiqWQ"]], "5": ["/sbin/killall5", 3, ["LccBsXvdFnxDUcsP5yiqWQ"]]}}